resumable_stream/__init__.py
resumable_stream/redis_adapter.py
resumable_stream/runtime.py
resumable_stream/types.py
resumable_stream-0.2.0.dist-info/METADATA
resumable_stream-0.2.0.dist-info/WHEEL
resumable_stream-0.2.0.dist-info/top_level.txt
resumable_stream-0.2.0.dist-info/RECORD
