Metadata-Version: 2.4
Name: resumable-stream
Version: 0.2.0
Summary: Library for wrapping async streams to allow client resumption after connection loss
License-Expression: MIT
Requires-Python: >=3.9
Requires-Dist: redis>=5.0.0
Provides-Extra: dev
Requires-Dist: pytest>=7.0.0; extra == "dev"
Requires-Dist: pytest-asyncio>=0.21.0; extra == "dev"
Requires-Dist: fakeredis>=2.20.0; extra == "dev"
Requires-Dist: ruff>=0.1.0; extra == "dev"
